{
  "diasUteis": [
    {
      "linha": 1,
      "nome": "Linha 01",
      "tipo": "um",
      "sublinha": null,
      "horarios": [
        "06:10",
        "06:50",
        "07:30",
        "08:35",
        "09:40",
        "11:10",
        "11:50",
        "12:30",
        "13:15",
        "14:10",
        "15:10",
        "15:50",
        "16:30",
        "17:10",
        "17:55",
        "18:50",
        "19:40"
      ],
      "itinerario": [
        "ESCOLA DE MÚSICA",
        "BELAS ARTES",
        "CAD 2",
        "LETRAS",
        "CIÊNCIA DA INFORMAÇÃO",
        "FAFICH",
        "FACE",
        "REITORIA",
        "PRAÇA DE SERVIÇOS",
        "BIBLIOTECA UNIVERSITÁRIA",
        "REITORIA",
        "UNID. ADM. III",
        "UNID. II",
        "AV. ANTONIO ABRAHÃO CARAM (EM FRENTE AO RESTAURANTE FARROUPILHA)",
        "CENTRO ESPORTIVO",
        "VETERINÁRIA",
        "AV. PRESIDENTE CARLOS LUZ (EM FRENTE MAC DONALD'S)",
        "EEFFTO",
        "ODONTOLOGIA",
        "ESTAÇÃO ECOLÓGICA",
        "VETERINÁRIA",
        "FARMÁCIA",
        "SETORIAL II",
        "FÍSICA",
        "ENG. ELÉTRICA",
        "CNEN/CDTN",
        "COLÉGIO TÉCNICO",
        "QUÍMICA",
        "ICEX",
        "ENGENHARIA",
        "FAFICH",
        "CIÊNCIA DA INFORMAÇÃO",
        "LETRAS",
        "CAD 2",
        "BELAS ARTES",
        "ESCOLA DE MÚSICA"
      ]
    },
    {
      "linha": 2,
      "nome": "Linha 02",
      "tipo": "dois",
      "sublinha": null,
      "horarios": [
        "05:55",
        "06:30",
        "07:10",
        "07:50",
        "09:05",
        "10:20",
        "14:30",
        "15:30",
        "16:10",
        "16:50",
        "19:20",
        "20:00",
        "20:50",
        "21:35",
        "22:30"
      ],
      "itinerario": [
        "ESCOLA DE MÚSICA",
        "BELAS ARTES",
        "CAD 2",
        "LETRAS",
        "CIÊNCIA DA INFORMAÇÃO",
        "FAFICH",
        "FACE",
        "REITORIA",
        "PRAÇA DE SERVIÇOS",
        "BIBLIOTECA UNIVERSITÁRIA",
        "REITORIA",
        "UNID. ADM. III",
        "UNID. II",
        "AV. ANTÔNIO ABRAHÃO CARAM (EM FRENTE AO RESTAURANTE FARROUPILHA)",
        "CENTRO ESPORTIVO",
        "VETERINÁRIA",
        "AV. PRESIDENTE CARLOS LUZ (EM FRENTE MAC DONALD'S)",
        "EEFFTO",
        "ODONTOLOGIA",
        "ESTAÇÃO ECOLOGICA",
        "VETERINÁRIA",
        "FARMÁCIA",
        "SETORIAL II",
        "FÍSICA",
        "ENG. ELÉTRICA",
        "CNEN/CDTN",
        "COLÉGIO TÉCNICO",
        "QUÍMICA",
        "ICEX",
        "ENGENHARIA",
        "GEOCIÊNCIAS",
        "SETORIAL I",
        "FAE",
        "CENTRO PEDAGÓGICO",
        "CRECHE",
        "BELAS ARTES",
        "ESCOLA DE MÚSICA"
      ]
    },
    {
      "linha": 2,
      "nome": "Linha 02",
      "tipo": "dois",
      "sublinha": "Retorno na Área Militar",
      "horarios": ["11:30", "12:10", "12:50", "13:45", "17:30", "18:20"],
      "itinerario": [
        "ESCOLA DE MÚSICA",
        "BELAS ARTES",
        "CAD 2",
        "LETRAS",
        "CIÊNCIA DA INFORMAÇÃO",
        "FAFICH",
        "FACE",
        "REITORIA",
        "PRAÇA DE SERVIÇOS",
        "BIBLIOTECA UNIVERSITÁRIA",
        "REITORIA",
        "UNID. ADM. III",
        "UNID. II",
        "AV. ANTÔNIO ABRAHÃO CARAM (EM FRENTE AO RESTAURANTE FARROUPILHA)",
        "CENTRO ESPORTIVO",
        "VETERINÁRIA",
        "AV. PRESIDENTE CARLOS LUZ (EM FRENTE MAC DONALD'S)",
        "EEFFTO",
        "ODONTOLOGIA",
        "ESTAÇÃO ECOLOGICA",
        "VETERINÁRIA",
        "FARMÁCIA",
        "SETORIAL II",
        "FÍSICA",
        "ENG. ELÉTRICA",
        "CNEN/CDTN",
        "COLÉGIO TÉCNICO",
        "QUÍMICA",
        "ICEX",
        "ENGENHARIA",
        "GEOCIÊNCIAS",
        "SETORIAL I",
        "FAE",
        "CENTRO PEDAGÓGICO",
        "CRECHE",
        "BELAS ARTES",
        "ESCOLA DE MÚSICA"
      ]
    },
    {
      "linha": 3,
      "nome": "Linha 03",
      "tipo": "tres",
      "sublinha": null,
      "horarios": [
        "05:40",
        "06:20",
        "07:00",
        "07:40",
        "08:20",
        "09:20",
        "10:00",
        "10:40",
        "14:55",
        "16:00",
        "16:40",
        "19:05",
        "20:30",
        "21:10",
        "21:50",
        "22:10"
      ],
      "itinerario": [
        "ESCOLA DE MÚSICA",
        "BELAS ARTES",
        "CRECHE",
        "CENTRO PEDAGÓGICO",
        "FAE",
        "SETORIAL I",
        "GEOCIÊNCIAS",
        "ENGENHARIA",
        "PRAÇA DE SERVIÇOS",
        "BIBLIOTECA UNIVERSITÁRIA",
        "REITORIA",
        "CAD 1",
        "ICB",
        "BIOTÉRIO CENTRAL",
        "FARMÁCIA",
        "VETERINÁRIA",
        "ODONTOLOGIA",
        "ESTAÇÃO ECOLÓGICA",
        "EEFFTO",
        "AV. PRES. CARLOS LUZ (EM FRENTE MC DONALD'S)",
        "VETERINÁRIA",
        "AV. C",
        "AV. ABRAHÃO CARAN (EM FRENTE AO RESTAURANTE FARROUPILHA)",
        "UNID. II (DAST/FUNDEP)",
        "UNID. ADM. III (DAP/DRCA/DRH/COPEVE/PROJETO MANUELZÃO/EDUCAÇÃO A DISTÂNCIA/ESTUDOS TRANSCIPLINARES/ESTUDOS DE CRIMINALIDADE E SEGURANÇA/ESTUDOS SOBRE ENSINO SUPERIOR E POLÍTICAS PÚBLICAS)",
        "REITORIA",
        "RUA PROF. EDUARDO M. GUIMARÃES",
        "FAFICH",
        "CIÊNCIA DA INFORMAÇÃO",
        "LETRAS",
        "BELAS ARTES",
        "ESCOLA DE MÚSICA"
      ]
    },
    {
      "linha": 3,
      "nome": "Linha 03",
      "tipo": "tres",
      "sublinha": "Retorno na Área Militar",
      "horarios": [
        "11:20",
        "12:00",
        "12:40",
        "13:30",
        "17:20",
        "18:10",
        "22:50"
      ],
      "itinerario": [
        "ESCOLA DE MÚSICA",
        "BELAS ARTES",
        "CRECHE",
        "CENTRO PEDAGÓGICO",
        "FAE",
        "SETORIAL I",
        "GEOCIÊNCIAS",
        "ENGENHARIA",
        "PRAÇA DE SERVIÇOS",
        "BIBLIOTECA UNIVERSITÁRIA",
        "REITORIA",
        "CAD 1",
        "ICB",
        "BIOTÉRIO CENTRAL",
        "FARMÁCIA",
        "VETERINÁRIA",
        "ODONTOLOGIA",
        "ESTAÇÃO ECOLÓGICA",
        "EEFFTO",
        "AV. PRES. CARLOS LUZ (EM FRENTE MC DONALD'S)",
        "VETERINÁRIA",
        "AV. C",
        "AV. ABRAHÃO CARAN (EM FRENTE AO RESTAURANTE FARROUPILHA)",
        "UNID. II (DAST/FUNDEP)",
        "UNID. ADM. III (DAP/DRCA/DRH/COPEVE/PROJETO MANUELZÃO/EDUCAÇÃO A DISTÂNCIA/ESTUDOS TRANSCIPLINARES/ESTUDOS DE CRIMINALIDADE E SEGURANÇA/ESTUDOS SOBRE ENSINO SUPERIOR E POLÍTICAS PÚBLICAS)",
        "REITORIA",
        "RUA PROF. EDUARDO M. GUIMARÃES",
        "FAFICH",
        "CIÊNCIA DA INFORMAÇÃO",
        "LETRAS",
        "BELAS ARTES",
        "ESCOLA DE MÚSICA"
      ]
    },
    {
      "linha": 3,
      "nome": "Linha 03",
      "tipo": "tres",
      "sublinha": "Atendimento ao BH-Tec",
      "horarios": ["07:40", "17:20"],
      "itinerario": [
        "ESCOLA DE MÚSICA",
        "BELAS ARTES",
        "CRECHE",
        "CENTRO PEDAGÓGICO",
        "FAE",
        "SETORIAL I",
        "GEOCIÊNCIAS",
        "ENGENHARIA",
        "PRAÇA DE SERVIÇOS",
        "BIBLIOTECA UNIVERSITÁRIA",
        "REITORIA",
        "CAD 1",
        "ICB",
        "BIOTÉRIO CENTRAL",
        "FARMÁCIA",
        "VETERINÁRIA",
        "ODONTOLOGIA",
        "ESTAÇÃO ECOLÓGICA",
        "EEFFTO",
        "USIMINAS",
        "RUA PROF. JOSÉ VIEIRA MENDONÇA",
        "BHTEC",
        "AV. PRES. CARLOS LUZ (EM FRENTE MAC DONALD'S)",
        "VETERINÁRIA",
        "AV. C",
        "AV. ABRAHÃO CARAN (EM FRENTE AO RESTAURANTE FARROUPILHA)",
        "UNID. II (DAST/FUNDEP)",
        "UNID. ADM. III (DAP/DRCA/DRH/COPEVE/PROJETO MANUELZÃO/EDUCAÇÃO A DISTÂNCIA/ESTUDOS TRANSCIPLINARES/ESTUDOS DE CRIMINALIDADE E SEGURANÇA/ESTUDOS SOBRE ENSINO SUPERIOR E POLÍTICAS PÚBLICAS)",
        "REITORIA",
        "RUA PROF. EDUARDO M. GUIMARAES",
        "FAFICH",
        "CIÊNCIA DA INFORMAÇÃO",
        "LETRAS",
        "BELAS ARTES",
        "ESCOLA DE MÚSICA"
      ]
    },
    {
      "linha": 4,
      "nome": "Linha 04",
      "tipo": "quatro",
      "sublinha": null,
      "horarios": [
        "06:00",
        "08:05",
        "08:50",
        "14:45",
        "15:40",
        "16:20",
        "20:15"
      ],
      "itinerario": [
        "ESCOLA DE MÚSICA",
        "BELAS ARTES",
        "CRECHE",
        "CENTRO PEDAGOGICO",
        "FAE",
        "SETORIAL I",
        "GEOCIÊNCIAS",
        "ENGENHARIA",
        "PRAÇA DE SERVIÇOS",
        "BIBLIOTECA UNIVERSITÁRIA",
        "REITORIA",
        "CAD 1",
        "ICB",
        "BIOTÉRIO CENTRAL",
        "FARMÁCIA",
        "VETERINÁRIA",
        "ESTAÇÃO ECOLÓGICA",
        "ODONTOLOGIA",
        "EEFFTO",
        "(RETORNO USIMINAS)",
        "EEFFTO",
        "ODONTOLOGIA",
        "ESTAÇÃO ECOLÓGICA",
        "VETERINÁRIA",
        "FARMÁCIA",
        "SET. II",
        "ICEX",
        "ENGENHARIA",
        "GEOCIÊNCIAS",
        "SET. I",
        "FAE",
        "CENTRO PEDAGÓGICO",
        "CRECHE",
        "BELAS ARTES",
        "ESCOLA DE MÚSICA"
      ]
    },
    {
      "linha": 4,
      "nome": "Linha 04",
      "tipo": "quatro",
      "sublinha": "Retorno na Área Militar",
      "horarios": [
        "11:00",
        "11:40",
        "12:20",
        "13:05",
        "13:55",
        "17:00",
        "17:40",
        "18:35"
      ],
      "itinerario": [
        "ESCOLA DE MÚSICA",
        "BELAS ARTES",
        "CRECHE",
        "CENTRO PEDAGOGICO",
        "FAE",
        "SETORIAL I",
        "GEOCIÊNCIAS",
        "ENGENHARIA",
        "PRAÇA DE SERVIÇOS",
        "BIBLIOTECA UNIVERSITÁRIA",
        "REITORIA",
        "CAD 1",
        "ICB",
        "BIOTÉRIO CENTRAL",
        "FARMÁCIA",
        "VETERINÁRIA",
        "ESTAÇÃO ECOLÓGICA",
        "ODONTOLOGIA",
        "EEFFTO",
        "(RETORNO USIMINAS)",
        "EEFFTO",
        "ODONTOLOGIA",
        "ESTAÇÃO ECOLÓGICA",
        "VETERINÁRIA",
        "FARMÁCIA",
        "SET. II",
        "ICEX",
        "ENGENHARIA",
        "GEOCIÊNCIAS",
        "SET. I",
        "FAE",
        "CENTRO PEDAGÓGICO",
        "CRECHE",
        "BELAS ARTES",
        "ESCOLA DE MÚSICA"
      ]
    },
    {
      "linha": 4,
      "nome": "Linha 04",
      "tipo": "quatro",
      "sublinha": "Atendimento ao Ponto McDonald's",
      "horarios": [
        "06:40",
        "07:20",
        "11:00",
        "11:40",
        "12:20",
        "13:05",
        "13:55",
        "17:00",
        "17:40"
      ],
      "itinerario": [
        "ESCOLA DE MÚSICA",
        "BELAS ARTES",
        "CRECHE",
        "CENTRO PEDAGÓGICO",
        "FAE",
        "SETORIAL I",
        "GEOCIÊNCIAS",
        "ENGENHARIA",
        "PRAÇA DE SERVIÇOS",
        "BIBLIOTECA UNIVERSITÁRIA",
        "REITORIA",
        "CAD 1",
        "ICB",
        "BIOTÉRIO CENTRAL",
        "FARMÁCIA",
        "VETERINÁRIA",
        "ESTAÇÃO ECOLÓGICA",
        "ODONTOLOGIA",
        "EEFFTO",
        "RETORNO NA AV. ALFREDO CAMARATE",
        "AV. PRES. CARLOS LUZ (EM FRENTE MC DONALD'S)",
        "EEFFTO",
        "ODONTOLOGIA",
        "ESTAÇÃO ECOLÓGICA",
        "VETERINÁRIA",
        "FARMÁCIA",
        "SET. II",
        "ICEX",
        "ENGENHARIA",
        "GEOCIÊNCIAS",
        "SET. I",
        "FAE",
        "CENTRO PEDAGÓGICO",
        "CRECHE",
        "BELAS ARTES",
        "ESCOLA DE MÚSICA"
      ]
    },
    {
      "linha": 4,
      "nome": "Linha 04",
      "tipo": "quatro",
      "sublinha": "Atendimento ao BH-Tec e McDonald's",
      "horarios": ["07:20", "12:20", "17:00"],
      "itinerario": [
        "ESCOLA DE MÚSICA",
        "BELAS ARTES",
        "CRECHE",
        "CENTRO PEDAGÓGICO",
        "FAE",
        "SETORIAL I",
        "GEOCIÊNCIAS",
        "ENGENHARIA",
        "PRAÇA DE SERVIÇOS",
        "BIBLIOTECA UNIVERSITÁRIA",
        "REITORIA",
        "CAD 1",
        "ICB",
        "BIOTÉRIO CENTRAL",
        "FARMÁCIA",
        "VETERINÁRIA",
        "ESTAÇÃO ECOLÓGICA",
        "ODONTOLOGIA",
        "EEFFTO",
        "RETORNO NA AV. ALFREDO CAMARATE",
        "AV. PRES. CARLOS LUZ (EM FRENTE MC DONALD'S",
        "RUA PROF. JOSÉ VIEIRA MENDONÇA",
        "BHTEC",
        "EEFFTO",
        "ODONTOLOGIA",
        "ESTAÇÃO ECOLÓGICA",
        "VETERINÁRIA",
        "FARMÁCIA",
        "SET. II",
        "ICEX",
        "ENGENHARIA",
        "GEOCIÊNCIAS",
        "SET. I",
        "FAE",
        "CENTRO PEDAGÓGICO",
        "CRECHE",
        "BELAS ARTES",
        "ESCOLA DE MÚSICA"
      ]
    }
  ],
  "sabado": [
    {
      "linha": 5,
      "nome": "Linha 02",
      "tipo": "dois-sabado",
      "sublinha": "Sábado",
      "horarios": ["11:00", "11:40", "12:20", "13:00", "13:40"],
      "itinerario": [
        "ESCOLA DE MÚSICA",
        "BELAS ARTES",
        "CAD 2",
        "LETRAS",
        "CIÊNCIA DA INFORMAÇÃO",
        "FAFICH",
        "FACE",
        "REITORIA",
        "PRAÇA DE SERVIÇOS",
        "BIBLIOTECA UNIVERSITÁRIA",
        "REITORIA",
        "UNID. ADM. III (DAP/DRCA/DRH/COPEVE/PROJETO MANUELZÃO/EDUCAÇÃO A DISTÂNCIA/ESTUDOS TRANSCIPLINARES/ESTUDOS DE CRIMINALIDADE E SEGURANÇA/ESTUDOS SOBRE ENSINO SUPERIOR E POLITICAS PÚBLICAS)",
        "UNID. II (DAST/FUNDEP)",
        "AV. ANTÔNIO ABRAHÃO CARAM (EM FRENTE AO RESTAURANTE FARROUPILHA)",
        "CENTRO ESPORTIVO",
        "VETERINÁRIA",
        "AV. PRESIDENTE CARLOS LUZ (EM FRENTE MAC DONALD'S)",
        "EEFFTO",
        "ODONTOLOGIA",
        "ESTAÇÃO ECOLOGICA",
        "VETERINÁRIA",
        "FARMÁCIA",
        "SETORIAL II",
        "FÍSICA",
        "ENG. ELÉTRICA (CPDE)",
        "CNEN/CDTN",
        "COLÉGIO TÉCNICO",
        "QUÍMICA",
        "ICEX",
        "ENGENHARIA",
        "GEOCIÊNCIAS",
        "SETORIAL I",
        "FAE",
        "CENTRO PEDAGÓGICO",
        "CRECHE",
        "BELAS ARTES",
        "ESCOLA DE MÚSICA"
      ]
    }
  ],
  "feriasRecessos": [
    {
      "linha": 6,
      "nome": "Linha 02",
      "tipo": "dois-ferias",
      "sublinha": "Férias e Recessos",
      "horarios": [
        "05:55",
        "06:40",
        "07:20",
        "08:05",
        "09:10",
        "10:40",
        "11:30",
        "12:10",
        "12:50",
        "13:50",
        "14:40",
        "15:30",
        "16:10",
        "16:50",
        "17:30",
        "18:20",
        "19:20",
        "20:00"
      ],
      "itinerario": [
        "ESCOLA DE MÚSICA",
        "BELAS ARTES",
        "CAD 2",
        "LETRAS",
        "CIÊNCIA DA INFORMAÇÃO",
        "FAFICH",
        "FACE",
        "REITORIA",
        "PRAÇA DE SERVIÇOS",
        "BIBLIOTECA UNIVERSITÁRIA",
        "REITORIA",
        "UNID. ADM. III (DAP/DRCA/DRH/COPEVE/PROJETO MANUELZÃO/EDUCAÇÃO A DISTÂNCIA/ESTUDOS TRANSCIPLINARES/ESTUDOS DE CRIMINALIDADE E SEGURANÇA/ESTUDOS SOBRE ENSINO SUPERIOR E POLITICAS PÚBLICAS)",
        "UNID. II (DAST/FUNDEP)",
        "AV. ANTÔNIO ABRAHÃO CARAM (EM FRENTE AO RESTAURANTE FARROUPILHA)",
        "CENTRO ESPORTIVO",
        "VETERINÁRIA",
        "AV. PRESIDENTE CARLOS LUZ (EM FRENTE MAC DONALD'S)",
        "EEFFTO",
        "ODONTOLOGIA",
        "ESTAÇÃO ECOLOGICA",
        "VETERINÁRIA",
        "FARMÁCIA",
        "SETORIAL II",
        "FÍSICA",
        "ENG. ELÉTRICA (CPDE)",
        "CNEN/CDTN",
        "COLÉGIO TÉCNICO",
        "QUÍMICA",
        "ICEX",
        "ENGENHARIA",
        "GEOCIÊNCIAS",
        "SETORIAL I",
        "FAE",
        "CENTRO PEDAGÓGICO",
        "CRECHE",
        "BELAS ARTES",
        "ESCOLA DE MÚSICA"
      ]
    }
  ]
}
